unbuiltins/__init__.py
unbuiltins/_types.py
unbuiltins/constants.py
unbuiltins/not_collections.py
unbuiltins/not_itertools.py
unbuiltins-0.2.2.dist-info/LICENSE
unbuiltins-0.2.2.dist-info/METADATA
unbuiltins-0.2.2.dist-info/WHEEL
unbuiltins-0.2.2.dist-info/top_level.txt
unbuiltins-0.2.2.dist-info/RECORD
