Metadata-Version: 2.1
Name: unbuiltins
Version: 0.2.2
Summary: What you'd expect to find in the Python builtins
Home-page: https://github.com/jorenham/python-unbuiltins/
Author: Joren Hammudoglu
License: UNKNOWN
Platform: UNKNOWN
Classifier: Intended Audience :: Developers
Classifier: Topic :: Software Development :: Libraries :: Python Modules
Classifier: Programming Language :: Python :: 3
Classifier: License :: OSI Approved :: GNU General Public License v3 (GPLv3)
Classifier: Operating System :: POSIX
Requires-Python: >=3.8.0
